pure_pagination/__init__.py
pure_pagination/mixins.py
pure_pagination/models.py
pure_pagination/paginator.py
pure_pagination/tests.py
pure_pagination/templates/pure_pagination/pagination-bootstrap.html
pure_pagination/templates/pure_pagination/pagination.html
nick_test_pagination-1.0.0.dist-info/LICENSE.txt
nick_test_pagination-1.0.0.dist-info/METADATA
nick_test_pagination-1.0.0.dist-info/WHEEL
nick_test_pagination-1.0.0.dist-info/top_level.txt
nick_test_pagination-1.0.0.dist-info/RECORD
